{
  "version": 1,
  "author": "Uri Shaked",
  "editor": "wokwi",
  "parts": [
    {
      "type": "wokwi-dip-switch-8",
      "id": "sw1",
      "top": -176.5,
      "left": -353.7,
      "rotate": 90,
      "attrs": {}
    },
    {
      "type": "wokwi-clock-generator",
      "id": "clock1",
      "top": -355.2,
      "left": -115.2,
      "attrs": { "frequency": "10000" }
    },
    { "type": "wokwi-vcc", "id": "pwr1", "top": -229.64, "left": -374.4, "attrs": {} },
    {
      "type": "wokwi-slide-switch",
      "id": "sw2",
      "top": -370,
      "left": -35.3,
      "attrs": { "value": "1" }
    },
    {
      "type": "wokwi-pushbutton",
      "id": "btn1",
      "top": -349,
      "left": 19.2,
      "attrs": { "color": "grey", "label": "Step", "bounce": "0", "key": "s" }
    },
    { "type": "wokwi-vcc", "id": "pwr3", "top": -373.64, "left": 105.6, "attrs": {} },
    {
      "type": "board-tt-block-input",
      "id": "ttin",
      "top": -228.13,
      "left": 14.4,
      "attrs": { "verilogRole": "input" }
    },
    {
      "type": "wokwi-pushbutton",
      "id": "btn2",
      "top": -301,
      "left": -134.4,
      "attrs": { "color": "grey", "label": "RESET", "bounce": "0", "key": "r" }
    },
    { "type": "wokwi-gnd", "id": "gnd1", "top": -259.2, "left": -163.8, "attrs": {} },
    {
      "type": "board-tt-block-output",
      "id": "ttout",
      "top": 1202.27,
      "left": 1540.8,
      "attrs": { "verilogRole": "output" }
    },
    {
      "type": "board-tt-block-bidirectional-io",
      "id": "ttio0",
      "top": 385.02,
      "left": -129.6,
      "attrs": { "verilogRole": "bidirectional", "verilogBit": "0" }
    },
    {
      "type": "board-tt-block-bidirectional-io",
      "id": "ttio1",
      "top": 423.42,
      "left": -129.6,
      "attrs": { "verilogRole": "bidirectional", "verilogBit": "1" }
    },
    {
      "type": "board-tt-block-bidirectional-io",
      "id": "ttio2",
      "top": 461.82,
      "left": -62.4,
      "attrs": { "verilogRole": "bidirectional", "verilogBit": "2" }
    },
    {
      "type": "board-tt-block-bidirectional-io",
      "id": "ttio3",
      "top": 500.22,
      "left": -62.4,
      "attrs": { "verilogRole": "bidirectional", "verilogBit": "3" }
    },
    {
      "type": "board-tt-block-bidirectional-io",
      "id": "ttio4",
      "top": 385.02,
      "left": -4.8,
      "attrs": { "verilogRole": "bidirectional", "verilogBit": "4" }
    },
    {
      "type": "board-tt-block-bidirectional-io",
      "id": "ttio5",
      "top": 423.42,
      "left": -4.8,
      "attrs": { "verilogRole": "bidirectional", "verilogBit": "5" }
    },
    {
      "type": "board-tt-block-bidirectional-io",
      "id": "ttio6",
      "top": 461.82,
      "left": -4.8,
      "attrs": { "verilogRole": "bidirectional", "verilogBit": "6" }
    },
    {
      "type": "board-tt-block-bidirectional-io",
      "id": "ttio7",
      "top": 500.22,
      "left": -4.8,
      "attrs": { "verilogRole": "bidirectional", "verilogBit": "7" }
    },
    {
      "type": "wokwi-resistor",
      "id": "r2",
      "top": -293.65,
      "left": -211.2,
      "attrs": { "value": "1000" }
    },
    { "type": "wokwi-vcc", "id": "pwr5", "top": -325.64, "left": -230.4, "attrs": {} },
    {
      "type": "wokwi-text",
      "id": "text1",
      "top": 345.82,
      "left": -93.85,
      "attrs": { "text": "Bidirectional I/O pins" }
    },
    { "type": "wokwi-gate-and-2", "id": "and1", "top": 19.2, "left": 460.8, "attrs": {} },
    { "type": "wokwi-flip-flop-d", "id": "flop1", "top": -19.2, "left": 672, "attrs": {} },
    {
      "type": "wokwi-gate-and-2",
      "id": "and2",
      "top": 115.4,
      "left": 758.6,
      "rotate": 90,
      "attrs": {}
    },
    { "type": "wokwi-flip-flop-d", "id": "flop2", "top": -19.2, "left": 892.8, "attrs": {} },
    { "type": "wokwi-gate-and-2", "id": "and3", "top": 57.6, "left": 336, "attrs": {} },
    { "type": "wokwi-gate-not", "id": "not1", "top": 48, "left": 230.4, "attrs": {} },
    { "type": "wokwi-gate-not", "id": "not2", "top": 96, "left": 230.4, "attrs": {} },
    { "type": "wokwi-flip-flop-d", "id": "flop3", "top": -19.2, "left": 1113.6, "attrs": {} },
    { "type": "wokwi-flip-flop-d", "id": "flop4", "top": -19.2, "left": 1324.8, "attrs": {} },
    {
      "type": "wokwi-gate-and-2",
      "id": "and4",
      "top": 115.4,
      "left": 950.6,
      "rotate": 90,
      "attrs": {}
    },
    {
      "type": "wokwi-gate-and-2",
      "id": "and5",
      "top": 115.4,
      "left": 1171.4,
      "rotate": 90,
      "attrs": {}
    },
    {
      "type": "wokwi-gate-and-2",
      "id": "and6",
      "top": 115.4,
      "left": 1382.6,
      "rotate": 90,
      "attrs": {}
    },
    { "type": "wokwi-gate-and-2", "id": "and7", "top": 240, "left": 460.8, "attrs": {} },
    { "type": "wokwi-flip-flop-d", "id": "flop5", "top": 201.6, "left": 672, "attrs": {} },
    {
      "type": "wokwi-gate-and-2",
      "id": "and8",
      "top": 336.2,
      "left": 729.8,
      "rotate": 90,
      "attrs": {}
    },
    { "type": "wokwi-flip-flop-d", "id": "flop6", "top": 201.6, "left": 864, "attrs": {} },
    { "type": "wokwi-gate-and-2", "id": "and9", "top": 278.4, "left": 336, "attrs": {} },
    { "type": "wokwi-gate-not", "id": "not3", "top": 268.8, "left": 230.4, "attrs": {} },
    { "type": "wokwi-flip-flop-d", "id": "flop7", "top": 201.6, "left": 1084.8, "attrs": {} },
    { "type": "wokwi-flip-flop-d", "id": "flop8", "top": 201.6, "left": 1296, "attrs": {} },
    {
      "type": "wokwi-gate-and-2",
      "id": "and10",
      "top": 336.2,
      "left": 921.8,
      "rotate": 90,
      "attrs": {}
    },
    {
      "type": "wokwi-gate-and-2",
      "id": "and11",
      "top": 336.2,
      "left": 1142.6,
      "rotate": 90,
      "attrs": {}
    },
    {
      "type": "wokwi-gate-and-2",
      "id": "and12",
      "top": 336.2,
      "left": 1353.8,
      "rotate": 90,
      "attrs": {}
    },
    { "type": "wokwi-gate-and-2", "id": "and13", "top": 585.6, "left": 451.2, "attrs": {} },
    { "type": "wokwi-flip-flop-d", "id": "flop9", "top": 547.2, "left": 662.4, "attrs": {} },
    {
      "type": "wokwi-gate-and-2",
      "id": "and14",
      "top": 681.8,
      "left": 720.2,
      "rotate": 90,
      "attrs": {}
    },
    { "type": "wokwi-flip-flop-d", "id": "flop10", "top": 547.2, "left": 854.4, "attrs": {} },
    { "type": "wokwi-gate-and-2", "id": "and15", "top": 624, "left": 326.4, "attrs": {} },
    { "type": "wokwi-gate-not", "id": "not5", "top": 662.4, "left": 220.8, "attrs": {} },
    { "type": "wokwi-flip-flop-d", "id": "flop11", "top": 547.2, "left": 1075.2, "attrs": {} },
    { "type": "wokwi-flip-flop-d", "id": "flop12", "top": 547.2, "left": 1286.4, "attrs": {} },
    {
      "type": "wokwi-gate-and-2",
      "id": "and16",
      "top": 681.8,
      "left": 912.2,
      "rotate": 90,
      "attrs": {}
    },
    {
      "type": "wokwi-gate-and-2",
      "id": "and17",
      "top": 681.8,
      "left": 1133,
      "rotate": 90,
      "attrs": {}
    },
    {
      "type": "wokwi-gate-and-2",
      "id": "and18",
      "top": 681.8,
      "left": 1344.2,
      "rotate": 90,
      "attrs": {}
    },
    { "type": "wokwi-gate-and-2", "id": "and19", "top": 940.8, "left": 441.6, "attrs": {} },
    { "type": "wokwi-flip-flop-d", "id": "flop13", "top": 902.4, "left": 652.8, "attrs": {} },
    {
      "type": "wokwi-gate-and-2",
      "id": "and20",
      "top": 1037,
      "left": 710.6,
      "rotate": 90,
      "attrs": {}
    },
    { "type": "wokwi-flip-flop-d", "id": "flop14", "top": 902.4, "left": 844.8, "attrs": {} },
    { "type": "wokwi-gate-and-2", "id": "and21", "top": 979.2, "left": 316.8, "attrs": {} },
    { "type": "wokwi-flip-flop-d", "id": "flop15", "top": 902.4, "left": 1065.6, "attrs": {} },
    { "type": "wokwi-flip-flop-d", "id": "flop16", "top": 902.4, "left": 1276.8, "attrs": {} },
    {
      "type": "wokwi-gate-and-2",
      "id": "and22",
      "top": 1037,
      "left": 902.6,
      "rotate": 90,
      "attrs": {}
    },
    {
      "type": "wokwi-gate-and-2",
      "id": "and23",
      "top": 1037,
      "left": 1123.4,
      "rotate": 90,
      "attrs": {}
    },
    {
      "type": "wokwi-gate-and-2",
      "id": "and24",
      "top": 1037,
      "left": 1334.6,
      "rotate": 90,
      "attrs": {}
    },
    {
      "type": "wokwi-led",
      "id": "led1",
      "top": 1208.8,
      "left": 1744.2,
      "rotate": 90,
      "attrs": { "color": "red", "flip": "1" }
    },
    {
      "type": "wokwi-led",
      "id": "led2",
      "top": 1237.6,
      "left": 1744.2,
      "rotate": 90,
      "attrs": { "color": "red", "flip": "1" }
    },
    {
      "type": "wokwi-led",
      "id": "led3",
      "top": 1266.4,
      "left": 1744.2,
      "rotate": 90,
      "attrs": { "color": "red", "flip": "1" }
    },
    {
      "type": "wokwi-led",
      "id": "led4",
      "top": 1295.2,
      "left": 1744.2,
      "rotate": 90,
      "attrs": { "color": "red", "flip": "1" }
    },
    { "type": "wokwi-gnd", "id": "gnd2", "top": 1344, "left": 1708.2, "attrs": {} },
    {
      "type": "wokwi-led",
      "id": "led5",
      "top": -109.2,
      "left": 791,
      "attrs": { "color": "red", "flip": "" }
    },
    { "type": "wokwi-gnd", "id": "gnd3", "top": -85.9, "left": 768.3, "rotate": 90, "attrs": {} },
    {
      "type": "wokwi-led",
      "id": "led6",
      "top": -109.2,
      "left": 983,
      "attrs": { "color": "red", "flip": "" }
    },
    { "type": "wokwi-gnd", "id": "gnd4", "top": -85.9, "left": 960.3, "rotate": 90, "attrs": {} },
    {
      "type": "wokwi-led",
      "id": "led7",
      "top": -109.2,
      "left": 1203.8,
      "attrs": { "color": "red", "flip": "" }
    },
    { "type": "wokwi-gnd", "id": "gnd5", "top": -85.9, "left": 1181.1, "rotate": 90, "attrs": {} },
    {
      "type": "wokwi-led",
      "id": "led8",
      "top": -109.2,
      "left": 1415,
      "attrs": { "color": "red", "flip": "" }
    },
    { "type": "wokwi-gnd", "id": "gnd6", "top": -85.9, "left": 1392.3, "rotate": 90, "attrs": {} },
    {
      "type": "wokwi-led",
      "id": "led9",
      "top": 130.8,
      "left": 743,
      "attrs": { "color": "red", "flip": "" }
    },
    { "type": "wokwi-gnd", "id": "gnd7", "top": 154.1, "left": 720.3, "rotate": 90, "attrs": {} },
    {
      "type": "wokwi-led",
      "id": "led10",
      "top": 130.8,
      "left": 935,
      "attrs": { "color": "red", "flip": "" }
    },
    { "type": "wokwi-gnd", "id": "gnd8", "top": 154.1, "left": 912.3, "rotate": 90, "attrs": {} },
    {
      "type": "wokwi-led",
      "id": "led11",
      "top": 130.8,
      "left": 1155.8,
      "attrs": { "color": "red", "flip": "" }
    },
    { "type": "wokwi-gnd", "id": "gnd9", "top": 154.1, "left": 1133.1, "rotate": 90, "attrs": {} },
    {
      "type": "wokwi-led",
      "id": "led12",
      "top": 140.4,
      "left": 1367,
      "attrs": { "color": "red", "flip": "" }
    },
    {
      "type": "wokwi-gnd",
      "id": "gnd10",
      "top": 163.7,
      "left": 1344.3,
      "rotate": 90,
      "attrs": {}
    },
    {
      "type": "wokwi-led",
      "id": "led13",
      "top": 486,
      "left": 733.4,
      "attrs": { "color": "red", "flip": "" }
    },
    { "type": "wokwi-gnd", "id": "gnd11", "top": 509.3, "left": 710.7, "rotate": 90, "attrs": {} },
    {
      "type": "wokwi-led",
      "id": "led14",
      "top": 486,
      "left": 925.4,
      "attrs": { "color": "red", "flip": "" }
    },
    { "type": "wokwi-gnd", "id": "gnd12", "top": 509.3, "left": 902.7, "rotate": 90, "attrs": {} },
    {
      "type": "wokwi-led",
      "id": "led15",
      "top": 486,
      "left": 1146.2,
      "attrs": { "color": "red", "flip": "" }
    },
    {
      "type": "wokwi-gnd",
      "id": "gnd13",
      "top": 509.3,
      "left": 1123.5,
      "rotate": 90,
      "attrs": {}
    },
    {
      "type": "wokwi-led",
      "id": "led16",
      "top": 486,
      "left": 1357.4,
      "attrs": { "color": "red", "flip": "" }
    },
    {
      "type": "wokwi-gnd",
      "id": "gnd14",
      "top": 509.3,
      "left": 1334.7,
      "rotate": 90,
      "attrs": {}
    },
    {
      "type": "wokwi-led",
      "id": "led17",
      "top": 841.2,
      "left": 723.8,
      "attrs": { "color": "red", "flip": "" }
    },
    { "type": "wokwi-gnd", "id": "gnd15", "top": 864.5, "left": 701.1, "rotate": 90, "attrs": {} },
    {
      "type": "wokwi-led",
      "id": "led18",
      "top": 841.2,
      "left": 915.8,
      "attrs": { "color": "red", "flip": "" }
    },
    { "type": "wokwi-gnd", "id": "gnd16", "top": 864.5, "left": 893.1, "rotate": 90, "attrs": {} },
    {
      "type": "wokwi-led",
      "id": "led19",
      "top": 841.2,
      "left": 1136.6,
      "attrs": { "color": "red", "flip": "" }
    },
    {
      "type": "wokwi-gnd",
      "id": "gnd17",
      "top": 864.5,
      "left": 1113.9,
      "rotate": 90,
      "attrs": {}
    },
    {
      "type": "wokwi-led",
      "id": "led20",
      "top": 841.2,
      "left": 1347.8,
      "attrs": { "color": "red", "flip": "" }
    },
    {
      "type": "wokwi-gnd",
      "id": "gnd18",
      "top": 864.5,
      "left": 1325.1,
      "rotate": 90,
      "attrs": {}
    },
    {
      "type": "wokwi-led",
      "id": "led21",
      "top": -65.6,
      "left": -283.8,
      "rotate": 180,
      "attrs": { "color": "red", "flip": "" }
    },
    {
      "type": "wokwi-gnd",
      "id": "gnd19",
      "top": -95.5,
      "left": -335.7,
      "rotate": 90,
      "attrs": {}
    },
    {
      "type": "wokwi-led",
      "id": "led22",
      "top": -65.6,
      "left": -255,
      "rotate": 180,
      "attrs": { "color": "red", "flip": "" }
    },
    {
      "type": "wokwi-led",
      "id": "led23",
      "top": -65.6,
      "left": -226.2,
      "rotate": 180,
      "attrs": { "color": "red", "flip": "" }
    },
    {
      "type": "wokwi-led",
      "id": "led24",
      "top": -65.6,
      "left": -197.4,
      "rotate": 180,
      "attrs": { "color": "red", "flip": "" }
    },
    {
      "type": "wokwi-led",
      "id": "led25",
      "top": -65.6,
      "left": -159,
      "rotate": 180,
      "attrs": { "color": "magenta", "flip": "" }
    },
    {
      "type": "wokwi-led",
      "id": "led26",
      "top": -65.6,
      "left": -130.2,
      "rotate": 180,
      "attrs": { "color": "magenta", "flip": "" }
    },
    {
      "type": "wokwi-led",
      "id": "led27",
      "top": -65.6,
      "left": -82.2,
      "rotate": 180,
      "attrs": { "color": "green", "flip": "" }
    },
    {
      "type": "wokwi-led",
      "id": "led29",
      "top": 870,
      "left": 474.6,
      "attrs": { "color": "blue", "flip": "1" }
    },
    {
      "type": "wokwi-gnd",
      "id": "gnd20",
      "top": 893.7,
      "left": 517.3,
      "rotate": 270,
      "attrs": {}
    },
    {
      "type": "wokwi-gate-or-2",
      "id": "or1",
      "top": 441.8,
      "left": 749,
      "rotate": 90,
      "attrs": {}
    },
    {
      "type": "wokwi-gate-or-2",
      "id": "or2",
      "top": 441.8,
      "left": 941,
      "rotate": 90,
      "attrs": {}
    },
    {
      "type": "wokwi-gate-or-2",
      "id": "or3",
      "top": 441.8,
      "left": 1161.8,
      "rotate": 90,
      "attrs": {}
    },
    {
      "type": "wokwi-gate-or-2",
      "id": "or4",
      "top": 441.8,
      "left": 1373,
      "rotate": 90,
      "attrs": {}
    },
    {
      "type": "wokwi-gate-or-2",
      "id": "or5",
      "top": 787.4,
      "left": 739.4,
      "rotate": 90,
      "attrs": {}
    },
    {
      "type": "wokwi-gate-or-2",
      "id": "or6",
      "top": 787.4,
      "left": 931.4,
      "rotate": 90,
      "attrs": {}
    },
    {
      "type": "wokwi-gate-or-2",
      "id": "or7",
      "top": 787.4,
      "left": 1152.2,
      "rotate": 90,
      "attrs": {}
    },
    {
      "type": "wokwi-gate-or-2",
      "id": "or8",
      "top": 787.4,
      "left": 1363.4,
      "rotate": 90,
      "attrs": {}
    },
    {
      "type": "wokwi-gate-or-2",
      "id": "or9",
      "top": 1142.6,
      "left": 729.8,
      "rotate": 90,
      "attrs": {}
    },
    {
      "type": "wokwi-gate-or-2",
      "id": "or10",
      "top": 1142.6,
      "left": 921.8,
      "rotate": 90,
      "attrs": {}
    },
    {
      "type": "wokwi-gate-or-2",
      "id": "or11",
      "top": 1142.6,
      "left": 1142.6,
      "rotate": 90,
      "attrs": {}
    },
    {
      "type": "wokwi-gate-or-2",
      "id": "or12",
      "top": 1142.6,
      "left": 1353.8,
      "rotate": 90,
      "attrs": {}
    }
  ],
  "connections": [
    [ "pwr1:VCC", "sw1:8a", "red", [ "v0" ] ],
    [ "pwr1:VCC", "sw1:7a", "red", [ "v0" ] ],
    [ "pwr1:VCC", "sw1:6a", "red", [ "v0" ] ],
    [ "pwr1:VCC", "sw1:5a", "red", [ "v0" ] ],
    [ "pwr1:VCC", "sw1:4a", "red", [ "v0" ] ],
    [ "pwr1:VCC", "sw1:1a", "red", [ "v0" ] ],
    [ "pwr1:VCC", "sw1:2a", "red", [ "v0" ] ],
    [ "pwr1:VCC", "sw1:3a", "red", [ "v0" ] ],
    [ "sw2:1", "clock1:CLK", "blue", [ "h-19.2", "v-57.6" ] ],
    [ "sw1:1b", "ttin:EXTIN0", "green", [ "h0" ] ],
    [ "sw1:2b", "ttin:EXTIN1", "green", [ "h0" ] ],
    [ "ttin:EXTIN2", "sw1:3b", "green", [ "h0" ] ],
    [ "ttin:EXTIN3", "sw1:4b", "green", [ "h0" ] ],
    [ "sw1:5b", "ttin:EXTIN4", "magenta", [ "h0" ] ],
    [ "ttin:EXTIN5", "sw1:6b", "magenta", [ "h0" ] ],
    [ "sw1:7b", "ttin:EXTIN6", "green", [ "h0" ] ],
    [ "sw1:8b", "ttin:EXTIN7", "green", [ "v0" ] ],
    [ "sw2:2", "ttin:EXTCLK", "blue", [ "v0" ] ],
    [ "btn1:1.l", "sw2:3", "blue", [ "h0" ] ],
    [ "pwr3:VCC", "btn1:2.r", "red", [ "v0" ] ],
    [ "btn2:2.l", "gnd1:GND", "black", [ "h0" ] ],
    [ "ttin:EXTRST_N", "btn2:1.r", "orange", [ "h-38.4", "v-96" ] ],
    [ "btn2:1.l", "r2:2", "green", [ "h0" ] ],
    [ "pwr5:VCC", "r2:1", "red", [ "v0" ] ],
    [ "and1:OUT", "flop2:CLK", "green", [ "v0", "h134.4" ] ],
    [ "and1:OUT", "flop1:CLK", "green", [ "v0", "h9.6" ] ],
    [ "and3:OUT", "and1:B", "cyan", [ "v0", "h28.8" ] ],
    [ "and3:OUT", "and2:B", "green", [ "v0", "h240" ] ],
    [ "not1:OUT", "and3:A", "green", [ "v0" ] ],
    [ "not2:OUT", "and3:B", "green", [ "v0" ] ],
    [ "and1:OUT", "flop3:CLK", "green", [ "v0", "h297.6" ] ],
    [ "and1:OUT", "flop4:CLK", "green", [ "v0", "h441.6" ] ],
    [ "and3:OUT", "and4:B", "green", [ "v0", "h374.4" ] ],
    [ "and3:OUT", "and5:B", "green", [ "v0", "h518.4" ] ],
    [ "and3:OUT", "and6:B", "cyan", [ "v0", "h662.4" ] ],
    [ "and2:A", "flop1:Q", "green", [ "v-96" ] ],
    [ "and4:A", "flop2:Q", "green", [ "v-96" ] ],
    [ "and5:A", "flop3:Q", "green", [ "v0" ] ],
    [ "and6:A", "flop4:Q", "green", [ "v0" ] ],
    [ "and7:OUT", "flop6:CLK", "green", [ "v0", "h134.4" ] ],
    [ "and7:OUT", "flop5:CLK", "green", [ "v0", "h9.6" ] ],
    [ "and9:OUT", "and7:B", "cyan", [ "v0", "h28.8" ] ],
    [ "and9:OUT", "and8:B", "green", [ "v0", "h240" ] ],
    [ "not3:OUT", "and9:A", "green", [ "v0" ] ],
    [ "and7:OUT", "flop7:CLK", "green", [ "v0", "h297.6" ] ],
    [ "and7:OUT", "flop8:CLK", "green", [ "v0", "h441.6" ] ],
    [ "and9:OUT", "and10:B", "green", [ "v0", "h374.4" ] ],
    [ "and9:OUT", "and11:B", "green", [ "v0", "h518.4" ] ],
    [ "and9:OUT", "and12:B", "cyan", [ "v0", "h662.4" ] ],
    [ "and8:A", "flop5:Q", "green", [ "v-96" ] ],
    [ "and10:A", "flop6:Q", "green", [ "v-96" ] ],
    [ "and11:A", "flop7:Q", "green", [ "v0" ] ],
    [ "and12:A", "flop8:Q", "green", [ "v0" ] ],
    [ "and13:OUT", "flop10:CLK", "green", [ "v0", "h134.4" ] ],
    [ "and13:OUT", "flop9:CLK", "green", [ "v0", "h9.6" ] ],
    [ "and15:OUT", "and13:B", "cyan", [ "v0", "h28.8" ] ],
    [ "and15:OUT", "and14:B", "green", [ "v0", "h240" ] ],
    [ "not5:OUT", "and15:B", "green", [ "v0" ] ],
    [ "and13:OUT", "flop11:CLK", "green", [ "v0", "h297.6" ] ],
    [ "and13:OUT", "flop12:CLK", "green", [ "v0", "h441.6" ] ],
    [ "and15:OUT", "and16:B", "green", [ "v0", "h374.4" ] ],
    [ "and15:OUT", "and17:B", "green", [ "v0", "h518.4" ] ],
    [ "and15:OUT", "and18:B", "cyan", [ "v0", "h662.4" ] ],
    [ "and14:A", "flop9:Q", "green", [ "v-96" ] ],
    [ "and16:A", "flop10:Q", "green", [ "v-96" ] ],
    [ "and17:A", "flop11:Q", "green", [ "v0" ] ],
    [ "and18:A", "flop12:Q", "green", [ "v0" ] ],
    [ "and19:OUT", "flop14:CLK", "green", [ "v0", "h134.4" ] ],
    [ "and19:OUT", "flop13:CLK", "green", [ "v0", "h9.6" ] ],
    [ "and21:OUT", "and19:B", "cyan", [ "v0", "h28.8" ] ],
    [ "and21:OUT", "and20:B", "green", [ "v0", "h240" ] ],
    [ "and19:OUT", "flop15:CLK", "green", [ "v0", "h297.6" ] ],
    [ "and19:OUT", "flop16:CLK", "green", [ "v0", "h441.6" ] ],
    [ "and21:OUT", "and22:B", "green", [ "v0", "h374.4" ] ],
    [ "and21:OUT", "and23:B", "green", [ "v0", "h518.4" ] ],
    [ "and21:OUT", "and24:B", "cyan", [ "v0", "h662.4" ] ],
    [ "and20:A", "flop13:Q", "green", [ "v-96" ] ],
    [ "and22:A", "flop14:Q", "green", [ "v-96" ] ],
    [ "and23:A", "flop15:Q", "green", [ "v0" ] ],
    [ "and24:A", "flop16:Q", "green", [ "v0" ] ],
    [ "flop1:D", "flop5:D", "green", [ "h-57.6", "v-9.6" ] ],
    [ "flop9:D", "flop5:D", "green", [ "h-48", "v-326.4" ] ],
    [ "flop13:D", "flop9:D", "green", [ "h-38.4", "v-211.2" ] ],
    [ "flop2:D", "flop6:D", "green", [ "h-48", "v220.8" ] ],
    [ "flop10:D", "flop6:D", "green", [ "h-9.6", "v-336" ] ],
    [ "flop14:D", "flop10:D", "green", [ "h0", "v-240" ] ],
    [ "flop3:D", "flop7:D", "green", [ "h-67.2", "v220.8" ] ],
    [ "flop11:D", "flop7:D", "green", [ "h-28.8", "v-326.4" ] ],
    [ "flop15:D", "flop11:D", "green", [ "h-19.2", "v-336" ] ],
    [ "flop4:D", "flop8:D", "green", [ "h-57.6", "v211.2" ] ],
    [ "flop12:D", "flop8:D", "green", [ "h-19.2", "v-336" ] ],
    [ "flop16:D", "flop12:D", "green", [ "h-9.6", "v-336" ] ],
    [ "ttin:IN0", "flop4:D", "green", [ "h1152", "v115.2" ] ],
    [ "ttin:IN1", "flop3:D", "green", [ "h931.2", "v124.8" ] ],
    [ "ttin:IN2", "flop2:D", "green", [ "h729.6", "v105.6" ] ],
    [ "ttin:IN3", "flop1:D", "green", [ "h499.2", "v96" ] ],
    [ "ttin:IN4", "not1:IN", "magenta", [ "h86.4", "v124.8" ] ],
    [ "not3:IN", "not1:IN", "magenta", [ "v0", "h-28.8", "v-211.2" ] ],
    [ "and15:A", "not3:IN", "magenta", [ "h-124.8", "v-288" ] ],
    [ "and21:A", "and15:A", "magenta", [ "h-115.2", "v-326.4" ] ],
    [ "ttin:IN5", "not2:IN", "magenta", [ "h76.8", "v249.6" ] ],
    [ "and9:B", "not2:IN", "magenta", [ "h-144", "v-9.6" ] ],
    [ "not5:IN", "and9:B", "magenta", [ "v0", "h-28.8", "v-364.8" ] ],
    [ "and21:B", "not5:IN", "magenta", [ "h-124.8", "v-316.8" ] ],
    [ "led1:A", "ttout:EXTOUT0", "green", [ "h0" ] ],
    [ "led2:A", "ttout:EXTOUT1", "green", [ "h-48", "v-19.2" ] ],
    [ "led3:A", "ttout:EXTOUT2", "green", [ "h-57.6", "v-38.4" ] ],
    [ "led4:A", "ttout:EXTOUT3", "green", [ "h-67.2", "v-57.6" ] ],
    [ "gnd2:GND", "led4:C", "black", [ "v0" ] ],
    [ "gnd2:GND", "led3:C", "black", [ "v0" ] ],
    [ "gnd2:GND", "led2:C", "black", [ "v0" ] ],
    [ "gnd2:GND", "led1:C", "black", [ "v0" ] ],
    [ "gnd3:GND", "led5:C", "black", [ "v0" ] ],
    [ "led5:A", "flop1:Q", "green", [ "v0" ] ],
    [ "gnd4:GND", "led6:C", "black", [ "v0" ] ],
    [ "led6:A", "flop2:Q", "green", [ "v0" ] ],
    [ "gnd5:GND", "led7:C", "black", [ "v0" ] ],
    [ "led7:A", "flop3:Q", "green", [ "v0" ] ],
    [ "gnd6:GND", "led8:C", "black", [ "v0" ] ],
    [ "led8:A", "flop4:Q", "green", [ "v0" ] ],
    [ "gnd7:GND", "led9:C", "black", [ "v0" ] ],
    [ "led9:A", "flop5:Q", "green", [ "v0" ] ],
    [ "gnd8:GND", "led10:C", "black", [ "v0" ] ],
    [ "led10:A", "flop6:Q", "green", [ "v0" ] ],
    [ "gnd9:GND", "led11:C", "black", [ "v0" ] ],
    [ "led11:A", "flop7:Q", "green", [ "v0" ] ],
    [ "gnd10:GND", "led12:C", "black", [ "v0" ] ],
    [ "led12:A", "flop8:Q", "green", [ "v0" ] ],
    [ "gnd11:GND", "led13:C", "black", [ "v0" ] ],
    [ "gnd12:GND", "led14:C", "black", [ "v0" ] ],
    [ "gnd13:GND", "led15:C", "black", [ "v0" ] ],
    [ "gnd14:GND", "led16:C", "black", [ "v0" ] ],
    [ "led13:A", "flop9:Q", "green", [ "v0" ] ],
    [ "led14:A", "flop10:Q", "green", [ "v0" ] ],
    [ "led15:A", "flop11:Q", "green", [ "v0" ] ],
    [ "led16:A", "flop12:Q", "green", [ "v0" ] ],
    [ "gnd15:GND", "led17:C", "black", [ "v0" ] ],
    [ "gnd16:GND", "led18:C", "black", [ "v0" ] ],
    [ "gnd17:GND", "led19:C", "black", [ "v0" ] ],
    [ "gnd18:GND", "led20:C", "black", [ "v0" ] ],
    [ "led17:A", "flop13:Q", "green", [ "v0" ] ],
    [ "led18:A", "flop14:Q", "green", [ "v0" ] ],
    [ "led19:A", "flop15:Q", "green", [ "v0" ] ],
    [ "led20:A", "flop16:Q", "green", [ "v0" ] ],
    [ "led21:A", "sw1:1b", "green", [ "v0" ] ],
    [ "led22:A", "sw1:2b", "green", [ "v0" ] ],
    [ "led23:A", "sw1:3b", "green", [ "v0" ] ],
    [ "led24:A", "sw1:4b", "green", [ "v0" ] ],
    [ "led25:A", "sw1:5b", "magenta", [ "v0" ] ],
    [ "led26:A", "sw1:6b", "magenta", [ "v0" ] ],
    [ "led27:A", "sw1:7b", "green", [ "v0" ] ],
    [ "led27:C", "gnd19:GND", "green", [ "v0" ] ],
    [ "led26:C", "gnd19:GND", "green", [ "v0" ] ],
    [ "led25:C", "gnd19:GND", "green", [ "v0" ] ],
    [ "led24:C", "gnd19:GND", "green", [ "v0" ] ],
    [ "led23:C", "gnd19:GND", "green", [ "v0" ] ],
    [ "led22:C", "gnd19:GND", "green", [ "v0" ] ],
    [ "led21:C", "gnd19:GND", "green", [ "v0" ] ],
    [ "gnd20:GND", "led29:C", "black", [ "v0" ] ],
    [ "and8:OUT", "or1:B", "green", [ "v0" ] ],
    [ "and2:OUT", "or1:A", "green", [ "v0" ] ],
    [ "and10:OUT", "or2:B", "green", [ "v9.6" ] ],
    [ "or2:A", "and4:OUT", "green", [ "v0" ] ],
    [ "and11:OUT", "or3:B", "green", [ "v0" ] ],
    [ "or3:A", "and5:OUT", "green", [ "v0" ] ],
    [ "and12:OUT", "or4:B", "green", [ "v0" ] ],
    [ "and6:OUT", "or4:A", "green", [ "v0" ] ],
    [ "and14:OUT", "or5:B", "green", [ "v0" ] ],
    [ "and16:OUT", "or6:B", "green", [ "v0" ] ],
    [ "and17:OUT", "or7:B", "green", [ "v0" ] ],
    [ "and18:OUT", "or8:B", "green", [ "v0" ] ],
    [ "or5:A", "or1:OUT", "green", [ "v0" ] ],
    [ "or2:OUT", "or6:A", "green", [ "v0" ] ],
    [ "or7:A", "or3:OUT", "green", [ "v0" ] ],
    [ "or4:OUT", "or8:A", "green", [ "v0" ] ],
    [ "and20:OUT", "or9:B", "green", [ "v0" ] ],
    [ "and22:OUT", "or10:B", "green", [ "v0" ] ],
    [ "and23:OUT", "or11:B", "green", [ "v0" ] ],
    [ "and24:OUT", "or12:B", "green", [ "v9.6", "h9.6" ] ],
    [ "or9:A", "or5:OUT", "green", [ "v0" ] ],
    [ "or6:OUT", "or10:A", "green", [ "v0" ] ],
    [ "or7:OUT", "or11:A", "green", [ "v0" ] ],
    [ "or8:OUT", "or12:A", "green", [ "v0" ] ],
    [ "or12:OUT", "ttout:OUT0", "green", [ "v0" ] ],
    [ "or11:OUT", "ttout:OUT1", "green", [ "v0" ] ],
    [ "or10:OUT", "ttout:OUT2", "green", [ "v0" ] ],
    [ "or9:OUT", "ttout:OUT3", "green", [ "v0" ] ],
    [ "ttin:IN6", "and1:A", "green", [ "h336", "v153.6" ] ],
    [ "and7:A", "ttin:IN6", "green", [ "h-9.6", "v-355.2" ] ],
    [ "and13:A", "ttin:IN6", "green", [ "h0", "v-700.8" ] ],
    [ "and19:A", "ttin:IN6", "green", [ "h9.6", "v-614.4" ] ],
    [ "led29:A", "and19:A", "green", [ "v0", "h-38.4" ] ]
  ],
  "dependencies": {}
}